{
    "drivers": {
        "CBE": {
            "[]": 157,
            "['User Interface & Experience']": 99
        },
        "BOA": {
            "[]": 121,
            "['User Interface & Experience']": 45
        },
        "Dashen": {
            "['User Interface & Experience']": 113,
            "[]": 100
        }
    },
    "pain_points": {
        "CBE": {
            "['User Interface & Experience']": 11,
            "[]": 9
        },
        "BOA": {
            "['User Interface & Experience']": 40,
            "[]": 24
        },
        "Dashen": {
            "[]": 13,
            "['User Interface & Experience']": 5
        }
    },
    "recommendations": []
}